psdb/__init__.py
psdb/access_port.py
psdb/ble_tool.py
psdb/cordic_test.py
psdb/core_tool.py
psdb/dump_stats.py
psdb/exception.py
psdb/flash_tool.py
psdb/fus_tool.py
psdb/gdb_tool.py
psdb/hexdump.py
psdb/mem_ap_test.py
psdb/reg_dump_tool.py
psdb/scan_tool.py
psdb/srst_tool.py
psdb/block/__init__.py
psdb/block/bd.py
psdb/block/rambd.py
psdb/component/__init__.py
psdb/component/component.py
psdb/component/matcher.py
psdb/cpus/__init__.py
psdb/cpus/cortex.py
psdb/cpus/cortex_m0p.py
psdb/cpus/cortex_m33.py
psdb/cpus/cortex_m4.py
psdb/cpus/cortex_m7.py
psdb/devices/__init__.py
psdb/devices/device.py
psdb/devices/flash.py
psdb/devices/core/__init__.py
psdb/devices/core/bpu.py
psdb/devices/core/coresight_0x9.py
psdb/devices/core/cortex_subdevice.py
psdb/devices/core/dwt_m4.py
psdb/devices/core/fpb.py
psdb/devices/core/itm_m4.py
psdb/devices/core/scs_base.py
psdb/devices/core/scs_v6_m.py
psdb/devices/core/scs_v7_m.py
psdb/devices/core/scs_v8_m.py
psdb/devices/core/tpiu_m4.py
psdb/devices/msp432/__init__.py
psdb/devices/msp432/flctl.py
psdb/devices/stm32/__init__.py
psdb/devices/stm32/adc.py
psdb/devices/stm32/adc_12.py
psdb/devices/stm32/adc_14.py
psdb/devices/stm32/adc_16.py
psdb/devices/stm32/advanced_control_timer.py
psdb/devices/stm32/basic_timer.py
psdb/devices/stm32/cordic.py
psdb/devices/stm32/crs.py
psdb/devices/stm32/dac.py
psdb/devices/stm32/dma.py
psdb/devices/stm32/dma_mux.py
psdb/devices/stm32/flash_type1.py
psdb/devices/stm32/general_purpose_timer_16x1.py
psdb/devices/stm32/general_purpose_timer_16x2.py
psdb/devices/stm32/general_purpose_timer_16x4.py
psdb/devices/stm32/general_purpose_timer_32.py
psdb/devices/stm32/gpdma.py
psdb/devices/stm32/gpio.py
psdb/devices/stm32/lpuart.py
psdb/devices/stm32/octospi.py
psdb/devices/stm32/qspi.py
psdb/devices/stm32/usb.py
psdb/devices/stm32/usb_hs.py
psdb/devices/stm32/vrefbuf.py
psdb/devices/stm32c0/__init__.py
psdb/devices/stm32c0/flash.py
psdb/devices/stm32c0/pwr.py
psdb/devices/stm32c0/rcc.py
psdb-1.1.6.dist-info/LICENSE
psdb-1.1.6.dist-info/METADATA
psdb-1.1.6.dist-info/WHEEL
psdb-1.1.6.dist-info/entry_points.txt
psdb-1.1.6.dist-info/top_level.txt
psdb-1.1.6.dist-info/RECORD
