Metadata-Version: 2.2
Name: psdb
Version: 1.1.6
Summary: Package for interfacing with ARM-compatible debug probes
Home-page: https://github.com/tgree/psdb
Author: Terry Greeniaus
Author-email: terrygreeniaus@gmail.com
License: LGPLv2
Keywords: stlink xds110 arm swd fus stm32 msp432
Classifier: Operating System :: OS Independent
Classifier: Programming Language :: Python :: 3
Classifier: License :: OSI Approved :: GNU Lesser General Public License v2 (LGPLv2)
Requires-Python: >=3.0
License-File: LICENSE
Requires-Dist: btype>=0.1.4
Requires-Dist: libusb_package>=1.0.26.2
Requires-Dist: pyelftools
Requires-Dist: pyusb
Requires-Dist: tgcurses>=0.9.5
